driver2200087/runner.py
driver2200087/serialDecoder.py
driver2200087/__init__.py
driver2200087-0.6.1.dist-info/DESCRIPTION.rst
driver2200087-0.6.1.dist-info/RECORD
driver2200087-0.6.1.dist-info/WHEEL
driver2200087-0.6.1.dist-info/top_level.txt
driver2200087-0.6.1.dist-info/metadata.json
driver2200087-0.6.1.dist-info/pbr.json
driver2200087-0.6.1.dist-info/METADATA
