Metadata-Version: 2.0
Name: driver2200087
Version: 0.6.1
Summary: Python Package to interface with Radio Shack's 2200087 Multimeter
Home-page: https://github.com/chintal/2200087-Serial-Protocol
Author: Chintalagiri Shashank
Author-email: shashank@chintal.in
License: GPLv2
Keywords: driver multimeter acquisition
Platform: any
Classifier: Development Status :: 3 - Alpha
Classifier: Topic :: Scientific/Engineering :: Interface Engine/Protocol Translator
Classifier: Topic :: System :: Hardware :: Hardware Drivers
Classifier: License :: OSI Approved :: GNU General Public License v2 or later (GPLv2+)
Classifier: Programming Language :: Python
Classifier: Framework :: Twisted
Classifier: Intended Audience :: Science/Research
Classifier: Natural Language :: English
Classifier: Operating System :: OS Independent
Requires-Dist: crochet (>=1.4.0)
Requires-Dist: pyserial (>=2.7)
Requires-Dist: Twisted (>=15.2.1)
